a2ginputstream/__init__.py
a2ginputstream/cloud_inputstream.py
a2ginputstream/inputstream.py
a2ginputstream/local_inputstream.py
a2gpipelines-0.0.30.dist-info/METADATA
a2gpipelines-0.0.30.dist-info/WHEEL
a2gpipelines-0.0.30.dist-info/top_level.txt
a2gpipelines-0.0.30.dist-info/RECORD
