Metadata-Version: 2.1
Name: a2gpipelines
Version: 0.0.30
Summary: short package description
Author: DaniloAraneda
Author-email: danilo@alert2gain.com
Classifier: Programming Language :: Python :: 3
Classifier: License :: OSI Approved :: MIT License
Classifier: Operating System :: OS Independent
Requires-Python: >=3.10.7
